solution.v
`timescale 1ns / 1ps
`include "iob_lib.vh"

module circuit
  #(
    parameter W=32
    )
  (
   `INPUT(rst,1),
   `INPUT(clk,1),
   `INPUT(en,1),
   `INPUT(in,8),
   `OUTPUT(y,W)
   );

   `SIGNAL_SIGNED(inputNumber,8)
   `SIGNAL_SIGNED(result,W)
   `SIGNAL_SIGNED(result_N_1,W)

   `SIGNAL(cnt, 7) //7-bit counter as iterator

   `SIGNAL2OUT(y, result) //connect internal y to output

   //y shift register 
   `REG_ARE(clk, rst, 1'b0, cnt!=99, result_N_1, result)

   //iteration counter
   `COUNTER_ARE(clk, rst, cnt!=99, cnt)

   //compute next why
   `COMB inputNumber = in;
   `COMB result = result_N_1*2 +inputNumber;

   
   
endmodule

solution_tb.v
`timescale 1ns / 1ps
`include "iob_lib.vh"

`define W 32

module circuit_tb;

   `CLOCK(clk, 10)
   `RESET(rst, 1, 10)
   `SIGNAL(en, 1)
   `SIGNAL_OUT(y, `W)

   `SIGNAL(in, 8)

   integer i;
   
   initial begin
      $dumpfile("circuit.vcd");
      $dumpvars();
      en=0;
      for (i=0; i<100; i=i+1) begin
        in =$random;
        @(posedge clk) #10 en=1; $display("Iteration %d: Input %d Output %d",i+1, $signed (in), $signed(y));
      end

      @(posedge clk) #100 $finish;

   end 

   circuit
     #(
       .W(`W)
       ) 
   c0
     (
      .rst(rst),
      .clk(clk),
      .en(en),
      .in(in),
      .y(y)
      );


endmodule

circuit.vcd
$date
	Tue Nov 17 22:17:06 2020
$end
$version
	Icarus Verilog
$end
$timescale
	1ps
$end
$scope module circuit_tb $end
$var wire 32 ! y [31:0] $end
$var reg 1 " clk $end
$var reg 1 # en $end
$var reg 8 $ in [7:0] $end
$var reg 1 % rst $end
$var integer 32 & i [31:0] $end
$scope module c0 $end
$var wire 1 " clk $end
$var wire 1 # en $end
$var wire 8 ' in [7:0] $end
$var wire 1 % rst $end
$var wire 32 ( y [31:0] $end
$var reg 7 ) cnt [6:0] $end
$var reg 8 * inputNumber [7:0] $end
$var reg 32 + result [31:0] $end
$var reg 32 , result_N_1 [31:0] $end
$upscope $end
$upscope $end
$enddefinitions $end
#0
$dumpvars
bx ,
bx +
b100100 *
bx )
bx (
b100100 '
b0 &
0%
b100100 $
0#
1"
bx !
$end
#1000
b100100 !
b100100 (
b100100 +
b0 )
b0 ,
1%
#5000
0"
#10000
1"
#11000
0%
#15000
0"
#20000
b1 )
b100100 ,
b11111111111111111111111111001001 !
b11111111111111111111111111001001 (
b11111111111111111111111111001001 +
b10000001 *
1"
b10000001 $
b10000001 '
b1 &
1#
#25000
0"
#30000
b11111111111111111111111111001001 ,
b10 )
b11111111111111111111111110011011 !
b11111111111111111111111110011011 (
b11111111111111111111111110011011 +
b1001 *
1"
b1001 $
b1001 '
b10 &
#35000
0"
#40000
b11 )
b11111111111111111111111110011011 ,
b11111111111111111111111110011001 !
b11111111111111111111111110011001 (
b11111111111111111111111110011001 +
b1100011 *
1"
b1100011 $
b1100011 '
b11 &
#45000
0"
#50000
b11111111111111111111111110011001 ,
b100 )
b11111111111111111111111100111111 !
b11111111111111111111111100111111 (
b11111111111111111111111100111111 +
b1101 *
1"
b1101 $
b1101 '
b100 &
#55000
0"
#60000
b101 )
b11111111111111111111111100111111 ,
b11111111111111111111111000001011 !
b11111111111111111111111000001011 (
b11111111111111111111111000001011 +
b10001101 *
1"
b10001101 $
b10001101 '
b101 &
#65000
0"
#70000
b11111111111111111111111000001011 ,
b110 )
b11111111111111111111110001111011 !
b11111111111111111111110001111011 (
b11111111111111111111110001111011 +
b1100101 *
1"
b1100101 $
b1100101 '
b110 &
#75000
0"
#80000
b111 )
b11111111111111111111110001111011 ,
b11111111111111111111100100001000 !
b11111111111111111111100100001000 (
b11111111111111111111100100001000 +
b10010 *
1"
b10010 $
b10010 '
b111 &
#85000
0"
#90000
b11111111111111111111100100001000 ,
b1000 )
b11111111111111111111001000010001 !
b11111111111111111111001000010001 (
b11111111111111111111001000010001 +
b1 *
1"
b1 $
b1 '
b1000 &
#95000
0"
#100000
b1001 )
b11111111111111111111001000010001 ,
b11111111111111111110010000101111 !
b11111111111111111110010000101111 (
b11111111111111111110010000101111 +
b1101 *
1"
b1101 $
b1101 '
b1001 &
#105000
0"
#110000
b11111111111111111110010000101111 ,
b1010 )
b11111111111111111100100011010100 !
b11111111111111111100100011010100 (
b11111111111111111100100011010100 +
b1110110 *
1"
b1110110 $
b1110110 '
b1010 &
#115000
0"
#120000
b1011 )
b11111111111111111100100011010100 ,
b11111111111111111001000111100101 !
b11111111111111111001000111100101 (
b11111111111111111001000111100101 +
b111101 *
1"
b111101 $
b111101 '
b1011 &
#125000
0"
#130000
b11111111111111111001000111100101 ,
b1100 )
b11111111111111110010001110110111 !
b11111111111111110010001110110111 (
b11111111111111110010001110110111 +
b11101101 *
1"
b11101101 $
b11101101 '
b1100 &
#135000
0"
#140000
b1101 )
b11111111111111110010001110110111 ,
b11111111111111100100011011111010 !
b11111111111111100100011011111010 (
b11111111111111100100011011111010 +
b10001100 *
1"
b10001100 $
b10001100 '
b1101 &
#145000
0"
#150000
b11111111111111100100011011111010 ,
b1110 )
b11111111111111001000110111101101 !
b11111111111111001000110111101101 (
b11111111111111001000110111101101 +
b11111001 *
1"
b11111001 $
b11111001 '
b1110 &
#155000
0"
#160000
b1111 )
b11111111111111001000110111101101 ,
b11111111111110010001101110100000 !
b11111111111110010001101110100000 (
b11111111111110010001101110100000 +
b11000110 *
1"
b11000110 $
b11000110 '
b1111 &
#165000
0"
#170000
b11111111111110010001101110100000 ,
b10000 )
b11111111111100100011011100000101 !
b11111111111100100011011100000101 (
b11111111111100100011011100000101 +
b11000101 *
1"
b11000101 $
b11000101 '
b10000 &
#175000
0"
#180000
b10001 )
b11111111111100100011011100000101 ,
b11111111111001000110110110110100 !
b11111111111001000110110110110100 (
b11111111111001000110110110110100 +
b10101010 *
1"
b10101010 $
b10101010 '
b10001 &
#185000
0"
#190000
b11111111111001000110110110110100 ,
b10010 )
b11111111110010001101101101001101 !
b11111111110010001101101101001101 (
b11111111110010001101101101001101 +
b11100101 *
1"
b11100101 $
b11100101 '
b10010 &
#195000
0"
#200000
b10011 )
b11111111110010001101101101001101 ,
b11111111100100011011011100010001 !
b11111111100100011011011100010001 (
b11111111100100011011011100010001 +
b1110111 *
1"
b1110111 $
b1110111 '
b10011 &
#205000
0"
#210000
b11111111100100011011011100010001 ,
b10100 )
b11111111001000110110111000110100 !
b11111111001000110110111000110100 (
b11111111001000110110111000110100 +
b10010 *
1"
b10010 $
b10010 '
b10100 &
#215000
0"
#220000
b10101 )
b11111111001000110110111000110100 ,
b11111110010001101101101111110111 !
b11111110010001101101101111110111 (
b11111110010001101101101111110111 +
b10001111 *
1"
b10001111 $
b10001111 '
b10101 &
#225000
0"
#230000
b11111110010001101101101111110111 ,
b10110 )
b11111100100011011011011111100000 !
b11111100100011011011011111100000 (
b11111100100011011011011111100000 +
b11110010 *
1"
b11110010 $
b11110010 '
b10110 &
#235000
0"
#240000
b10111 )
b11111100100011011011011111100000 ,
b11111001000110110110111110001110 !
b11111001000110110110111110001110 (
b11111001000110110110111110001110 +
b11001110 *
1"
b11001110 $
b11001110 '
b10111 &
#245000
0"
#250000
b11111001000110110110111110001110 ,
b11000 )
b11110010001101101101111100000100 !
b11110010001101101101111100000100 (
b11110010001101101101111100000100 +
b11101000 *
1"
b11101000 $
b11101000 '
b11000 &
#255000
0"
#260000
b11001 )
b11110010001101101101111100000100 ,
b11100100011011011011110111001101 !
b11100100011011011011110111001101 (
b11100100011011011011110111001101 +
b11000101 *
1"
b11000101 $
b11000101 '
b11001 &
#265000
0"
#270000
b11100100011011011011110111001101 ,
b11010 )
b11001000110110110111101111110110 !
b11001000110110110111101111110110 (
b11001000110110110111101111110110 +
b1011100 *
1"
b1011100 $
b1011100 '
b11010 &
#275000
0"
#280000
b11011 )
b11001000110110110111101111110110 ,
b10010001101101101111011110101001 !
b10010001101101101111011110101001 (
b10010001101101101111011110101001 +
b10111101 *
1"
b10111101 $
b10111101 '
b11011 &
#285000
0"
#290000
b10010001101101101111011110101001 ,
b11100 )
b100011011011011110111101111111 !
b100011011011011110111101111111 (
b100011011011011110111101111111 +
b101101 *
1"
b101101 $
b101101 '
b11100 &
#295000
0"
#300000
b11101 )
b100011011011011110111101111111 ,
b1000110110110111101111101100011 !
b1000110110110111101111101100011 (
b1000110110110111101111101100011 +
b1100101 *
1"
b1100101 $
b1100101 '
b11101 &
#305000
0"
#310000
b1000110110110111101111101100011 ,
b11110 )
b10001101101101111011111100101001 !
b10001101101101111011111100101001 (
b10001101101101111011111100101001 +
b1100011 *
1"
b1100011 $
b1100011 '
b11110 &
#315000
0"
#320000
b11111 )
b10001101101101111011111100101001 ,
b11011011011110111111001011100 !
b11011011011110111111001011100 (
b11011011011110111111001011100 +
b1010 *
1"
b1010 $
b1010 '
b11111 &
#325000
0"
#330000
b11011011011110111111001011100 ,
b100000 )
b110110110111101111110000111000 !
b110110110111101111110000111000 (
b110110110111101111110000111000 +
b10000000 *
1"
b10000000 $
b10000000 '
b100000 &
#335000
0"
#340000
b100001 )
b110110110111101111110000111000 ,
b1101101101111011111100010010000 !
b1101101101111011111100010010000 (
b1101101101111011111100010010000 +
b100000 *
1"
b100000 $
b100000 '
b100001 &
#345000
0"
#350000
b1101101101111011111100010010000 ,
b100010 )
b11011011011110111111000011001010 !
b11011011011110111111000011001010 (
b11011011011110111111000011001010 +
b10101010 *
1"
b10101010 $
b10101010 '
b100010 &
#355000
0"
#360000
b100011 )
b11011011011110111111000011001010 ,
b10110110111101111110000100110001 !
b10110110111101111110000100110001 (
b10110110111101111110000100110001 +
b10011101 *
1"
b10011101 $
b10011101 '
b100011 &
#365000
0"
#370000
b10110110111101111110000100110001 ,
b100100 )
b1101101111011111100000111111000 !
b1101101111011111100000111111000 (
b1101101111011111100000111111000 +
b10010110 *
1"
b10010110 $
b10010110 '
b100100 &
#375000
0"
#380000
b100101 )
b1101101111011111100000111111000 ,
b11011011110111111000010000000011 !
b11011011110111111000010000000011 (
b11011011110111111000010000000011 +
b10011 *
1"
b10011 $
b10011 '
b100101 &
#385000
0"
#390000
b11011011110111111000010000000011 ,
b100110 )
b10110111101111110000100000010011 !
b10110111101111110000100000010011 (
b10110111101111110000100000010011 +
b1101 *
1"
b1101 $
b1101 '
b100110 &
#395000
0"
#400000
b100111 )
b10110111101111110000100000010011 ,
b1101111011111100001000001111001 !
b1101111011111100001000001111001 (
b1101111011111100001000001111001 +
b1010011 *
1"
b1010011 $
b1010011 '
b100111 &
#405000
0"
#410000
b1101111011111100001000001111001 ,
b101000 )
b11011110111111000010000101011101 !
b11011110111111000010000101011101 (
b11011110111111000010000101011101 +
b1101011 *
1"
b1101011 $
b1101011 '
b101000 &
#415000
0"
#420000
b101001 )
b11011110111111000010000101011101 ,
b10111101111110000100001010001111 !
b10111101111110000100001010001111 (
b10111101111110000100001010001111 +
b11010101 *
1"
b11010101 $
b11010101 '
b101001 &
#425000
0"
#430000
b10111101111110000100001010001111 ,
b101010 )
b1111011111100001000010100100000 !
b1111011111100001000010100100000 (
b1111011111100001000010100100000 +
b10 *
1"
b10 $
b10 '
b101010 &
#435000
0"
#440000
b101011 )
b1111011111100001000010100100000 ,
b11110111111000010000100111101110 !
b11110111111000010000100111101110 (
b11110111111000010000100111101110 +
b10101110 *
1"
b10101110 $
b10101110 '
b101011 &
#445000
0"
#450000
b11110111111000010000100111101110 ,
b101100 )
b11101111110000100001001111111001 !
b11101111110000100001001111111001 (
b11101111110000100001001111111001 +
b11101 *
1"
b11101 $
b11101 '
b101100 &
#455000
0"
#460000
b101101 )
b11101111110000100001001111111001 ,
b11011111100001000010011111000001 !
b11011111100001000010011111000001 (
b11011111100001000010011111000001 +
b11001111 *
1"
b11001111 $
b11001111 '
b101101 &
#465000
0"
#470000
b11011111100001000010011111000001 ,
b101110 )
b10111111000010000100111110100101 !
b10111111000010000100111110100101 (
b10111111000010000100111110100101 +
b100011 *
1"
b100011 $
b100011 '
b101110 &
#475000
0"
#480000
b101111 )
b10111111000010000100111110100101 ,
b1111110000100001001111101010100 !
b1111110000100001001111101010100 (
b1111110000100001001111101010100 +
b1010 *
1"
b1010 $
b1010 '
b101111 &
#485000
0"
#490000
b1111110000100001001111101010100 ,
b110000 )
b11111100001000010011111001110010 !
b11111100001000010011111001110010 (
b11111100001000010011111001110010 +
b11001010 *
1"
b11001010 $
b11001010 '
b110000 &
#495000
0"
#500000
b110001 )
b11111100001000010011111001110010 ,
b11111000010000100111110100100000 !
b11111000010000100111110100100000 (
b11111000010000100111110100100000 +
b111100 *
1"
b111100 $
b111100 '
b110001 &
#505000
0"
#510000
b11111000010000100111110100100000 ,
b110010 )
b11110000100001001111101000110010 !
b11110000100001001111101000110010 (
b11110000100001001111101000110010 +
b11110010 *
1"
b11110010 $
b11110010 '
b110010 &
#515000
0"
#520000
b110011 )
b11110000100001001111101000110010 ,
b11100001000010011111001111101110 !
b11100001000010011111001111101110 (
b11100001000010011111001111101110 +
b10001010 *
1"
b10001010 $
b10001010 '
b110011 &
#525000
0"
#530000
b11100001000010011111001111101110 ,
b110100 )
b11000010000100111110100000011101 !
b11000010000100111110100000011101 (
b11000010000100111110100000011101 +
b1000001 *
1"
b1000001 $
b1000001 '
b110100 &
#535000
0"
#540000
b110101 )
b11000010000100111110100000011101 ,
b10000100001001111101000000010010 !
b10000100001001111101000000010010 (
b10000100001001111101000000010010 +
b11011000 *
1"
b11011000 $
b11011000 '
b110101 &
#545000
0"
#550000
b10000100001001111101000000010010 ,
b110110 )
b1000010011111010000010011100 !
b1000010011111010000010011100 (
b1000010011111010000010011100 +
b1111000 *
1"
b1111000 $
b1111000 '
b110110 &
#555000
0"
#560000
b110111 )
b1000010011111010000010011100 ,
b10000100111110100000011000001 !
b10000100111110100000011000001 (
b10000100111110100000011000001 +
b10001001 *
1"
b10001001 $
b10001001 '
b110111 &
#565000
0"
#570000
b10000100111110100000011000001 ,
b111000 )
b100001001111101000000101101101 !
b100001001111101000000101101101 (
b100001001111101000000101101101 +
b11101011 *
1"
b11101011 $
b11101011 '
b111000 &
#575000
0"
#580000
b111001 )
b100001001111101000000101101101 ,
b1000010011111010000001010010000 !
b1000010011111010000001010010000 (
b1000010011111010000001010010000 +
b10110110 *
1"
b10110110 $
b10110110 '
b111001 &
#585000
0"
#590000
b1000010011111010000001010010000 ,
b111010 )
b10000100111110100000010011100110 !
b10000100111110100000010011100110 (
b10000100111110100000010011100110 +
b11000110 *
1"
b11000110 $
b11000110 '
b111010 &
#595000
0"
#600000
b111011 )
b10000100111110100000010011100110 ,
b1001111101000000100101111010 !
b1001111101000000100101111010 (
b1001111101000000100101111010 +
b10101110 *
1"
b10101110 $
b10101110 '
b111011 &
#605000
0"
#610000
b1001111101000000100101111010 ,
b111100 )
b10011111010000001001010110000 !
b10011111010000001001010110000 (
b10011111010000001001010110000 +
b10111100 *
1"
b10111100 $
b10111100 '
b111100 &
#615000
0"
#620000
b111101 )
b10011111010000001001010110000 ,
b100111110100000010010110001010 !
b100111110100000010010110001010 (
b100111110100000010010110001010 +
b101010 *
1"
b101010 $
b101010 '
b111101 &
#625000
0"
#630000
b100111110100000010010110001010 ,
b111110 )
b1001111101000000100101100011111 !
b1001111101000000100101100011111 (
b1001111101000000100101100011111 +
b1011 *
1"
b1011 $
b1011 '
b111110 &
#635000
0"
#640000
b111111 )
b1001111101000000100101100011111 ,
b10011111010000001001011010101111 !
b10011111010000001001011010101111 (
b10011111010000001001011010101111 +
b1110001 *
1"
b1110001 $
b1110001 '
b111111 &
#645000
0"
#650000
b10011111010000001001011010101111 ,
b1000000 )
b111110100000010010110011100011 !
b111110100000010010110011100011 (
b111110100000010010110011100011 +
b10000101 *
1"
b10000101 $
b10000101 '
b1000000 &
#655000
0"
#660000
b1000001 )
b111110100000010010110011100011 ,
b1111101000000100101101000010101 !
b1111101000000100101101000010101 (
b1111101000000100101101000010101 +
b1001111 *
1"
b1001111 $
b1001111 '
b1000001 &
#665000
0"
#670000
b1111101000000100101101000010101 ,
b1000010 )
b11111010000001001011010001100101 !
b11111010000001001011010001100101 (
b11111010000001001011010001100101 +
b111011 *
1"
b111011 $
b111011 '
b1000010 &
#675000
0"
#680000
b1000011 )
b11111010000001001011010001100101 ,
b11110100000010010110100100000100 !
b11110100000010010110100100000100 (
b11110100000010010110100100000100 +
b111010 *
1"
b111010 $
b111010 '
b1000011 &
#685000
0"
#690000
b11110100000010010110100100000100 ,
b1000100 )
b11101000000100101101001010000110 !
b11101000000100101101001010000110 (
b11101000000100101101001010000110 +
b1111110 *
1"
b1111110 $
b1111110 '
b1000100 &
#695000
0"
#700000
b1000101 )
b11101000000100101101001010000110 ,
b11010000001001011010010100100001 !
b11010000001001011010010100100001 (
b11010000001001011010010100100001 +
b10101 *
1"
b10101 $
b10101 '
b1000101 &
#705000
0"
#710000
b11010000001001011010010100100001 ,
b1000110 )
b10100000010010110100101000110011 !
b10100000010010110100101000110011 (
b10100000010010110100101000110011 +
b11110001 *
1"
b11110001 $
b11110001 '
b1000110 &
#715000
0"
#720000
b1000111 )
b10100000010010110100101000110011 ,
b1000000100101101001010000111111 !
b1000000100101101001010000111111 (
b1000000100101101001010000111111 +
b11011001 *
1"
b11011001 $
b11011001 '
b1000111 &
#725000
0"
#730000
b1000000100101101001010000111111 ,
b1001000 )
b10000001001011010010100011100000 !
b10000001001011010010100011100000 (
b10000001001011010010100011100000 +
b1100010 *
1"
b1100010 $
b1100010 '
b1001000 &
#735000
0"
#740000
b1001001 )
b10000001001011010010100011100000 ,
b10010110100101001000001100 !
b10010110100101001000001100 (
b10010110100101001000001100 +
b1001100 *
1"
b1001100 $
b1001100 '
b1001001 &
#745000
0"
#750000
b10010110100101001000001100 ,
b1001010 )
b100101101001010001110110111 !
b100101101001010001110110111 (
b100101101001010001110110111 +
b10011111 *
1"
b10011111 $
b10011111 '
b1001010 &
#755000
0"
#760000
b1001011 )
b100101101001010001110110111 ,
b1001011010010100011011111101 !
b1001011010010100011011111101 (
b1001011010010100011011111101 +
b10001111 *
1"
b10001111 $
b10001111 '
b1001011 &
#765000
0"
#770000
b1001011010010100011011111101 ,
b1001100 )
b10010110100101000110111110010 !
b10010110100101000110111110010 (
b10010110100101000110111110010 +
b11111000 *
1"
b11111000 $
b11111000 '
b1001100 &
#775000
0"
#780000
b1001101 )
b10010110100101000110111110010 ,
b100101101001010001101110011011 !
b100101101001010001101110011011 (
b100101101001010001101110011011 +
b10110111 *
1"
b10110111 $
b10110111 '
b1001101 &
#785000
0"
#790000
b100101101001010001101110011011 ,
b1001110 )
b1001011010010100011011011010101 !
b1001011010010100011011011010101 (
b1001011010010100011011011010101 +
b10011111 *
1"
b10011111 $
b10011111 '
b1001110 &
#795000
0"
#800000
b1001111 )
b1001011010010100011011011010101 ,
b10010110100101000110111000000110 !
b10010110100101000110111000000110 (
b10010110100101000110111000000110 +
b1011100 *
1"
b1011100 $
b1011100 '
b1001111 &
#805000
0"
#810000
b10010110100101000110111000000110 ,
b1010000 )
b101101001010001101110001100111 !
b101101001010001101110001100111 (
b101101001010001101110001100111 +
b1011011 *
1"
b1011011 $
b1011011 '
b1010000 &
#815000
0"
#820000
b1010001 )
b101101001010001101110001100111 ,
b1011010010100011011100001010111 !
b1011010010100011011100001010111 (
b1011010010100011011100001010111 +
b10001001 *
1"
b10001001 $
b10001001 '
b1010001 &
#825000
0"
#830000
b1011010010100011011100001010111 ,
b1010010 )
b10110100101000110111000011110111 !
b10110100101000110111000011110111 (
b10110100101000110111000011110111 +
b1001001 *
1"
b1001001 $
b1001001 '
b1010010 &
#835000
0"
#840000
b1010011 )
b10110100101000110111000011110111 ,
b1101001010001101110000110111110 !
b1101001010001101110000110111110 (
b1101001010001101110000110111110 +
b11010000 *
1"
b11010000 $
b11010000 '
b1010011 &
#845000
0"
#850000
b1101001010001101110000110111110 ,
b1010100 )
b11010010100011011100001101010011 !
b11010010100011011100001101010011 (
b11010010100011011100001101010011 +
b11010111 *
1"
b11010111 $
b11010111 '
b1010100 &
#855000
0"
#860000
b1010101 )
b11010010100011011100001101010011 ,
b10100101000110111000011011110111 !
b10100101000110111000011011110111 (
b10100101000110111000011011110111 +
b1010001 *
1"
b1010001 $
b1010001 '
b1010101 &
#865000
0"
#870000
b10100101000110111000011011110111 ,
b1010110 )
b1001010001101110000110110000100 !
b1001010001101110000110110000100 (
b1001010001101110000110110000100 +
b10010110 *
1"
b10010110 $
b10010110 '
b1010110 &
#875000
0"
#880000
b1010111 )
b1001010001101110000110110000100 ,
b10010100011011100001101100010100 !
b10010100011011100001101100010100 (
b10010100011011100001101100010100 +
b1100 *
1"
b1100 $
b1100 '
b1010111 &
#885000
0"
#890000
b10010100011011100001101100010100 ,
b1011000 )
b101000110111000011010111101010 !
b101000110111000011010111101010 (
b101000110111000011010111101010 +
b11000010 *
1"
b11000010 $
b11000010 '
b1011000 &
#895000
0"
#900000
b1011001 )
b101000110111000011010111101010 ,
b1010001101110000110101110011100 !
b1010001101110000110101110011100 (
b1010001101110000110101110011100 +
b11001000 *
1"
b11001000 $
b11001000 '
b1011001 &
#905000
0"
#910000
b1010001101110000110101110011100 ,
b1011010 )
b10100011011100001101011110101111 !
b10100011011100001101011110101111 (
b10100011011100001101011110101111 +
b1110111 *
1"
b1110111 $
b1110111 '
b1011010 &
#915000
0"
#920000
b1011011 )
b10100011011100001101011110101111 ,
b1000110111000011010111110011011 !
b1000110111000011010111110011011 (
b1000110111000011010111110011011 +
b111101 *
1"
b111101 $
b111101 '
b1011011 &
#925000
0"
#930000
b1000110111000011010111110011011 ,
b1011100 )
b10001101110000110101111101001000 !
b10001101110000110101111101001000 (
b10001101110000110101111101001000 +
b10010 *
1"
b10010 $
b10010 '
b1011100 &
#935000
0"
#940000
b1011101 )
b10001101110000110101111101001000 ,
b11011100001101011111100001110 !
b11011100001101011111100001110 (
b11011100001101011111100001110 +
b1111110 *
1"
b1111110 $
b1111110 '
b1011101 &
#945000
0"
#950000
b11011100001101011111100001110 ,
b1011110 )
b110111000011010111111010001001 !
b110111000011010111111010001001 (
b110111000011010111111010001001 +
b1101101 *
1"
b1101101 $
b1101101 '
b1011110 &
#955000
0"
#960000
b1011111 )
b110111000011010111111010001001 ,
b1101110000110101111110101001011 !
b1101110000110101111110101001011 (
b1101110000110101111110101001011 +
b111001 *
1"
b111001 $
b111001 '
b1011111 &
#965000
0"
#970000
b1101110000110101111110101001011 ,
b1100000 )
b11011100001101011111101010110101 !
b11011100001101011111101010110101 (
b11011100001101011111101010110101 +
b11111 *
1"
b11111 $
b11111 '
b1100000 &
#975000
0"
#980000
b1100001 )
b11011100001101011111101010110101 ,
b10111000011010111111010100111101 !
b10111000011010111111010100111101 (
b10111000011010111111010100111101 +
b11010011 *
1"
b11010011 $
b11010011 '
b1100001 &
#985000
0"
#990000
b10111000011010111111010100111101 ,
b1100010 )
b1110000110101111110100111111111 !
b1110000110101111110100111111111 (
b1110000110101111110100111111111 +
b10000101 *
1"
b10000101 $
b10000101 '
b1100010 &
#995000
0"
#1000000
b1100011 )
b1110000110101111110100111111111 ,
b11100001101011111101010001110110 !
b11100001101011111101010001110110 (
b11100001101011111101010001110110 +
b1111000 *
1"
b1111000 $
b1111000 '
b1100011 &
#1005000
0"
#1010000
1"
b1100100 &
